mpagen/__init__.py
mpagen/__main__.py
mpagen/gen.py
mpagen/templates/__init__.py
mpagen/templates/base.jinja2
mpagen/templates/controller.jinja2
mpagen/templates/section_controller.jinja2
mpagen/templates/service.jinja2
mpagen/templates/utils.jinja2
mpagen/templates/view.jinja2
mpa_gen-0.2.dist-info/LICENSE
mpa_gen-0.2.dist-info/METADATA
mpa_gen-0.2.dist-info/WHEEL
mpa_gen-0.2.dist-info/entry_points.txt
mpa_gen-0.2.dist-info/top_level.txt
mpa_gen-0.2.dist-info/RECORD
