Metadata-Version: 2.1
Name: mpa-gen
Version: 0.2
Summary: Simple generator for Go multi-page site
Home-page: https://github.com/reddec/mpa-gen
Author: Baryshnikov Aleksandr (reddec)
Author-email: owner@reddec.net
License: UNKNOWN
Platform: UNKNOWN
Classifier: Programming Language :: Python :: 3.4
Classifier: License :: OSI Approved :: Apache Software License
Classifier: Topic :: Utilities
Requires-Dist: Jinja2 (~=2.10.1)
